[
    {
        "lat": 42.4071531,
        "lon": -71.1238539,
        "type": "health"
    },
    {
        "lat": 42.3820736,
        "lon": -71.1119136,
        "type": "health"
    },
    {
        "lat": 42.3658768,
        "lon": -71.1039555,
        "type": "health"
    },
    {
        "lat": 42.3722674,
        "lon": -71.1187497,
        "type": "health"
    },
    {
        "lat": 42.3746465,
        "lon": -71.1021313,
        "type": "health"
    },
    {
        "lat": 42.3785522,
        "lon": -71.1197149,
        "type": "health"
    },
    {
        "lat": 42.4164997,
        "lon": -71.11643649999999,
        "type": "health"
    },
    {
        "lat": 42.3801195,
        "lon": -71.1173017,
        "type": "health"
    },
    {
        "lat": 42.3663515,
        "lon": -71.1049627,
        "type": "health"
    },
    {
        "lat": 42.3816994,
        "lon": -71.097591,
        "type": "health"
    },
    {
        "lat": 42.3851222,
        "lon": -71.1059047,
        "type": "health"
    },
    {
        "lat": 42.3784937,
        "lon": -71.1196988,
        "type": "health"
    },
    {
        "lat": 42.4176264,
        "lon": -71.1578974,
        "type": "health"
    },
    {
        "lat": 42.3701089,
        "lon": -71.1022923,
        "type": "health"
    },
    {
        "lat": 42.3950175,
        "lon": -71.12178650000001,
        "type": "health"
    },
    {
        "lat": 42.3746983,
        "lon": -71.1046029,
        "type": "health"
    },
    {
        "lat": 42.4176186,
        "lon": -71.15790009999999,
        "type": "health"
    },
    {
        "lat": 42.3905235,
        "lon": -71.1524254,
        "type": "health"
    },
    {
        "lat": 42.3757224,
        "lon": -71.1070658,
        "type": "health"
    },
    {
        "lat": 42.3701984,
        "lon": -71.1620535,
        "type": "health"
    },
    {
        "lat": 42.3756052,
        "lon": -71.1471218,
        "type": "health"
    },
    {
        "lat": 42.3702968,
        "lon": -71.0951905,
        "type": "health"
    },
    {
        "lat": 42.3741195,
        "lon": -71.1344091,
        "type": "health"
    },
    {
        "lat": 42.3906714,
        "lon": -71.1523328,
        "type": "health"
    },
    {
        "lat": 42.39938799999999,
        "lon": -71.1101436,
        "type": "health"
    },
    {
        "lat": 42.4160004,
        "lon": -71.111171,
        "type": "health"
    },
    {
        "lat": 42.42078679999999,
        "lon": -71.1108141,
        "type": "health"
    },
    {
        "lat": 42.4177943,
        "lon": -71.15811860000001,
        "type": "health"
    },
    {
        "lat": 42.3756213,
        "lon": -71.1241707,
        "type": "health"
    },
    {
        "lat": 42.3906714,
        "lon": -71.1523327,
        "type": "health"
    },
    {
        "lat": 42.3747805,
        "lon": -71.1045778,
        "type": "health"
    },
    {
        "lat": 42.3922475,
        "lon": -71.1555259,
        "type": "health"
    },
    {
        "lat": 42.4177942,
        "lon": -71.1581188,
        "type": "health"
    },
    {
        "lat": 42.3850475,
        "lon": -71.1059179,
        "type": "health"
    },
    {
        "lat": 42.418752,
        "lon": -71.11240800000002,
        "type": "health"
    },
    {
        "lat": 42.3882732,
        "lon": -71.1197639,
        "type": "health"
    },
    {
        "lat": 42.4160472,
        "lon": -71.1111921,
        "type": "health"
    },
    {
        "lat": 42.39129140000001,
        "lon": -71.12054359999999,
        "type": "health"
    },
    {
        "lat": 42.4160518,
        "lon": -71.12754319999999,
        "type": "health"
    },
    {
        "lat": 42.395218,
        "lon": -71.1589206,
        "type": "health"
    },
    {
        "lat": 42.3722919,
        "lon": -71.0884284,
        "type": "health"
    },
    {
        "lat": 42.4149334,
        "lon": -71.1561474,
        "type": "health"
    },
    {
        "lat": 42.3917484,
        "lon": -71.1555951,
        "type": "health"
    },
    {
        "lat": 42.3969084,
        "lon": -71.0929192,
        "type": "health"
    },
    {
        "lat": 42.3973853,
        "lon": -71.1233807,
        "type": "health"
    },
    {
        "lat": 42.3679281,
        "lon": -71.1073675,
        "type": "health"
    },
    {
        "lat": 42.4182823,
        "lon": -71.10695729999999,
        "type": "health"
    },
    {
        "lat": 42.3906906,
        "lon": -71.152333,
        "type": "health"
    },
    {
        "lat": 42.4097387,
        "lon": -71.1057106,
        "type": "health"
    },
    {
        "lat": 42.3743705,
        "lon": -71.10385010000002,
        "type": "health"
    },
    {
        "lat": 42.390304,
        "lon": -71.14077309999999,
        "type": "health"
    },
    {
        "lat": 42.3951945,
        "lon": -71.1457427,
        "type": "health"
    },
    {
        "lat": 42.4176264,
        "lon": -71.1578974,
        "type": "health"
    },
    {
        "lat": 42.3956745,
        "lon": -71.12109339999999,
        "type": "health"
    },
    {
        "lat": 42.3975012,
        "lon": -71.1236303,
        "type": "health"
    },
    {
        "lat": 42.3748814,
        "lon": -71.10865679999999,
        "type": "health"
    },
    {
        "lat": 42.375547,
        "lon": -71.1469884,
        "type": "health"
    },
    {
        "lat": 42.4177943,
        "lon": -71.1581187,
        "type": "health"
    },
    {
        "lat": 42.3828733,
        "lon": -71.132384,
        "type": "health"
    },
    {
        "lat": 42.3897541,
        "lon": -71.1097454,
        "type": "health"
    },
    {
        "lat": 42.3132893,
        "lon": -71.1139766,
        "type": "health"
    },
    {
        "lat": 42.34437200000001,
        "lon": -71.1148571,
        "type": "health"
    },
    {
        "lat": 42.3390615,
        "lon": -71.16480910000001,
        "type": "health"
    },
    {
        "lat": 42.3513825,
        "lon": -71.1155252,
        "type": "health"
    },
    {
        "lat": 42.3356788,
        "lon": -71.1019213,
        "type": "health"
    },
    {
        "lat": 42.3440746,
        "lon": -71.0989723,
        "type": "health"
    },
    {
        "lat": 42.3620187,
        "lon": -71.1437467,
        "type": "health"
    },
    {
        "lat": 42.3658768,
        "lon": -71.1039555,
        "type": "health"
    },
    {
        "lat": 42.310964,
        "lon": -71.1039722,
        "type": "health"
    },
    {
        "lat": 42.3329447,
        "lon": -71.0918706,
        "type": "health"
    },
    {
        "lat": 42.3481289,
        "lon": -71.1501943,
        "type": "health"
    },
    {
        "lat": 42.3327877,
        "lon": -71.09182229999999,
        "type": "health"
    },
    {
        "lat": 42.3485449,
        "lon": -71.0909162,
        "type": "health"
    },
    {
        "lat": 42.3398798,
        "lon": -71.1045583,
        "type": "health"
    },
    {
        "lat": 42.3509842,
        "lon": -71.146072,
        "type": "health"
    },
    {
        "lat": 42.3202306,
        "lon": -71.09718090000001,
        "type": "health"
    },
    {
        "lat": 42.3663515,
        "lon": -71.1049627,
        "type": "health"
    },
    {
        "lat": 42.3108511,
        "lon": -71.1035203,
        "type": "health"
    },
    {
        "lat": 42.3357189,
        "lon": -71.1015243,
        "type": "health"
    },
    {
        "lat": 42.3259655,
        "lon": -71.14957679999999,
        "type": "health"
    },
    {
        "lat": 42.3387004,
        "lon": -71.1321669,
        "type": "health"
    },
    {
        "lat": 42.3420504,
        "lon": -71.12042060000002,
        "type": "health"
    },
    {
        "lat": 42.3374515,
        "lon": -71.1081799,
        "type": "health"
    },
    {
        "lat": 42.3356451,
        "lon": -71.104215,
        "type": "health"
    },
    {
        "lat": 42.35086099999999,
        "lon": -71.1178271,
        "type": "health"
    },
    {
        "lat": 42.34465609999999,
        "lon": -71.1106035,
        "type": "health"
    },
    {
        "lat": 42.3293235,
        "lon": -71.1071868,
        "type": "health"
    },
    {
        "lat": 42.323168,
        "lon": -71.167,
        "type": "health"
    },
    {
        "lat": 42.3701089,
        "lon": -71.1022923,
        "type": "health"
    },
    {
        "lat": 42.3367616,
        "lon": -71.1513556,
        "type": "health"
    },
    {
        "lat": 42.3440598,
        "lon": -71.0989136,
        "type": "health"
    },
    {
        "lat": 42.3444364,
        "lon": -71.1148783,
        "type": "health"
    },
    {
        "lat": 42.3445785,
        "lon": -71.11106149999999,
        "type": "health"
    },
    {
        "lat": 42.3350638,
        "lon": -71.10916879999999,
        "type": "health"
    },
    {
        "lat": 42.3489571,
        "lon": -71.1426625,
        "type": "health"
    },
    {
        "lat": 42.3443225,
        "lon": -71.1147253,
        "type": "health"
    },
    {
        "lat": 42.32576290000001,
        "lon": -71.146939,
        "type": "health"
    },
    {
        "lat": 42.3489117,
        "lon": -71.1427697,
        "type": "health"
    },
    {
        "lat": 42.3108149,
        "lon": -71.1035407,
        "type": "health"
    },
    {
        "lat": 42.3417953,
        "lon": -71.1234225,
        "type": "health"
    },
    {
        "lat": 42.3360547,
        "lon": -71.1086388,
        "type": "health"
    },
    {
        "lat": 42.3453704,
        "lon": -71.100629,
        "type": "health"
    },
    {
        "lat": 42.3367506,
        "lon": -71.1210076,
        "type": "health"
    },
    {
        "lat": 42.3424314,
        "lon": -71.1193539,
        "type": "health"
    },
    {
        "lat": 42.33739569999999,
        "lon": -71.14550400000002,
        "type": "health"
    },
    {
        "lat": 42.3439897,
        "lon": -71.0988467,
        "type": "health"
    },
    {
        "lat": 42.3353382,
        "lon": -71.1083244,
        "type": "health"
    },
    {
        "lat": 42.3427961,
        "lon": -71.13935529999999,
        "type": "health"
    },
    {
        "lat": 42.3448747,
        "lon": -71.12591139999999,
        "type": "health"
    },
    {
        "lat": 42.3701984,
        "lon": -71.1620535,
        "type": "health"
    },
    {
        "lat": 42.3377174,
        "lon": -71.1375635,
        "type": "health"
    },
    {
        "lat": 42.3344746,
        "lon": -71.1197134,
        "type": "health"
    },
    {
        "lat": 42.3525745,
        "lon": -71.1228908,
        "type": "health"
    },
    {
        "lat": 42.3446554,
        "lon": -71.1110116,
        "type": "health"
    },
    {
        "lat": 42.3489937,
        "lon": -71.0855495,
        "type": "health"
    },
    {
        "lat": 42.3702968,
        "lon": -71.0951905,
        "type": "health"
    },
    {
        "lat": 42.3679281,
        "lon": -71.1073675,
        "type": "health"
    },
    {
        "lat": 42.3454875,
        "lon": -71.1006979,
        "type": "health"
    },
    {
        "lat": 42.3243187,
        "lon": -71.1023003,
        "type": "health"
    },
    {
        "lat": 42.3518749,
        "lon": -71.1277413,
        "type": "health"
    },
    {
        "lat": 42.3647611,
        "lon": -71.0536983,
        "type": "health"
    },
    {
        "lat": 42.3555165,
        "lon": -71.0530382,
        "type": "health"
    },
    {
        "lat": 42.311926,
        "lon": -71.0686836,
        "type": "health"
    },
    {
        "lat": 42.3384005,
        "lon": -71.0748684,
        "type": "health"
    },
    {
        "lat": 42.3194323,
        "lon": -71.0450855,
        "type": "health"
    },
    {
        "lat": 42.3523302,
        "lon": -71.065302,
        "type": "health"
    },
    {
        "lat": 42.3369045,
        "lon": -71.0481343,
        "type": "health"
    },
    {
        "lat": 42.3638527,
        "lon": -71.06170089999999,
        "type": "health"
    },
    {
        "lat": 42.3590235,
        "lon": -71.0584106,
        "type": "health"
    },
    {
        "lat": 42.3194034,
        "lon": -71.0461466,
        "type": "health"
    },
    {
        "lat": 42.3512636,
        "lon": -71.0770994,
        "type": "health"
    },
    {
        "lat": 42.3481015,
        "lon": -71.0411061,
        "type": "health"
    },
    {
        "lat": 42.3480141,
        "lon": -71.064566,
        "type": "health"
    },
    {
        "lat": 42.348831,
        "lon": -71.0721366,
        "type": "health"
    },
    {
        "lat": 42.35733099999999,
        "lon": -71.05821399999999,
        "type": "health"
    },
    {
        "lat": 42.31474739999999,
        "lon": -71.0784706,
        "type": "health"
    },
    {
        "lat": 42.3500947,
        "lon": -71.0606782,
        "type": "health"
    },
    {
        "lat": 42.352401,
        "lon": -71.0635935,
        "type": "health"
    },
    {
        "lat": 42.3539891,
        "lon": -71.05811059999999,
        "type": "health"
    },
    {
        "lat": 42.3588847,
        "lon": -71.0553535,
        "type": "health"
    },
    {
        "lat": 42.3473046,
        "lon": -71.0819042,
        "type": "health"
    },
    {
        "lat": 42.3517396,
        "lon": -71.0726698,
        "type": "health"
    },
    {
        "lat": 42.3467174,
        "lon": -71.0694173,
        "type": "health"
    },
    {
        "lat": 42.3611928,
        "lon": -71.0866127,
        "type": "health"
    },
    {
        "lat": 42.348175,
        "lon": -71.0412781,
        "type": "health"
    },
    {
        "lat": 42.3631671,
        "lon": -71.0687306,
        "type": "health"
    },
    {
        "lat": 42.3347398,
        "lon": -71.0742333,
        "type": "health"
    },
    {
        "lat": 42.35117289999999,
        "lon": -71.0611259,
        "type": "health"
    },
    {
        "lat": 42.345831,
        "lon": -71.0643359,
        "type": "health"
    },
    {
        "lat": 42.3509804,
        "lon": -71.0575628,
        "type": "health"
    },
    {
        "lat": 42.35737839999999,
        "lon": -71.05573,
        "type": "health"
    },
    {
        "lat": 42.3369062,
        "lon": -71.048137,
        "type": "health"
    },
    {
        "lat": 42.3574449,
        "lon": -71.0593099,
        "type": "health"
    },
    {
        "lat": 42.3509525,
        "lon": -71.0715658,
        "type": "health"
    },
    {
        "lat": 42.3697053,
        "lon": -71.0395313,
        "type": "health"
    },
    {
        "lat": 42.3617049,
        "lon": -71.06533,
        "type": "health"
    },
    {
        "lat": 42.3515397,
        "lon": -71.0729115,
        "type": "health"
    },
    {
        "lat": 42.3535705,
        "lon": -71.0804418,
        "type": "health"
    },
    {
        "lat": 42.3592969,
        "lon": -71.0590812,
        "type": "health"
    },
    {
        "lat": 42.3330467,
        "lon": -71.0736404,
        "type": "health"
    },
    {
        "lat": 42.3369062,
        "lon": -71.048137,
        "type": "health"
    },
    {
        "lat": 42.3518033,
        "lon": -71.07215479999999,
        "type": "health"
    },
    {
        "lat": 42.3486211,
        "lon": -71.0663307,
        "type": "health"
    },
    {
        "lat": 42.3600283,
        "lon": -71.05317289999999,
        "type": "health"
    },
    {
        "lat": 42.3489937,
        "lon": -71.0855495,
        "type": "health"
    },
    {
        "lat": 42.3505461,
        "lon": -71.07675100000002,
        "type": "health"
    },
    {
        "lat": 42.3183336,
        "lon": -71.06397989999999,
        "type": "health"
    },
    {
        "lat": 42.3549953,
        "lon": -71.05682039999999,
        "type": "health"
    },
    {
        "lat": 42.336822,
        "lon": -71.0704717,
        "type": "health"
    },
    {
        "lat": 42.3574487,
        "lon": -71.0544159,
        "type": "health"
    },
    {
        "lat": 42.355174,
        "lon": -71.0558739,
        "type": "health"
    },
    {
        "lat": 42.362006,
        "lon": -71.0619151,
        "type": "health"
    },
    {
        "lat": 42.3529736,
        "lon": -71.06124129999999,
        "type": "health"
    },
    {
        "lat": 42.334523,
        "lon": -71.07405709999999,
        "type": "health"
    },
    {
        "lat": 42.3275375,
        "lon": -71.0672225,
        "type": "health"
    },
    {
        "lat": 42.3498022,
        "lon": -71.06724630000001,
        "type": "health"
    },
    {
        "lat": 42.3344782,
        "lon": -71.0755121,
        "type": "health"
    },
    {
        "lat": 42.3550135,
        "lon": -71.0587838,
        "type": "health"
    },
    {
        "lat": 42.352076,
        "lon": -71.063102,
        "type": "health"
    },
    {
        "lat": 42.3369311,
        "lon": -71.0481755,
        "type": "health"
    },
    {
        "lat": 42.3778838,
        "lon": -71.05680029999999,
        "type": "health"
    },
    {
        "lat": 42.372328,
        "lon": -71.038398,
        "type": "health"
    },
    {
        "lat": 42.3771729,
        "lon": -71.0642508,
        "type": "health"
    },
    {
        "lat": 42.4201308,
        "lon": -71.07263259999999,
        "type": "health"
    },
    {
        "lat": 42.3647611,
        "lon": -71.0536983,
        "type": "health"
    },
    {
        "lat": 42.3709916,
        "lon": -71.0348724,
        "type": "health"
    },
    {
        "lat": 42.4181807,
        "lon": -71.0760545,
        "type": "health"
    },
    {
        "lat": 42.3837634,
        "lon": -71.020263,
        "type": "health"
    },
    {
        "lat": 42.3697053,
        "lon": -71.0395313,
        "type": "health"
    },
    {
        "lat": 42.3961198,
        "lon": -71.0390879,
        "type": "health"
    },
    {
        "lat": 42.3850182,
        "lon": -71.0152859,
        "type": "health"
    },
    {
        "lat": 42.3648007,
        "lon": -71.0537232,
        "type": "health"
    },
    {
        "lat": 42.3942017,
        "lon": -71.0404267,
        "type": "health"
    },
    {
        "lat": 42.3687093,
        "lon": -71.03962349999999,
        "type": "health"
    },
    {
        "lat": 42.3868158,
        "lon": -71.080027,
        "type": "health"
    },
    {
        "lat": 42.4028993,
        "lon": -71.02011379999999,
        "type": "health"
    },
    {
        "lat": 42.3638527,
        "lon": -71.06170089999999,
        "type": "health"
    },
    {
        "lat": 42.3748004,
        "lon": -71.0381007,
        "type": "health"
    },
    {
        "lat": 42.38862930000001,
        "lon": -71.0365312,
        "type": "health"
    },
    {
        "lat": 42.3755695,
        "lon": -71.0650866,
        "type": "health"
    },
    {
        "lat": 42.4074064,
        "lon": -71.0757983,
        "type": "health"
    },
    {
        "lat": 42.3730519,
        "lon": -71.0853989,
        "type": "health"
    },
    {
        "lat": 42.3741547,
        "lon": -71.0335731,
        "type": "health"
    },
    {
        "lat": 42.4198588,
        "lon": -71.0727362,
        "type": "health"
    },
    {
        "lat": 42.3975646,
        "lon": -71.0313481,
        "type": "health"
    },
    {
        "lat": 42.4039519,
        "lon": -71.048669,
        "type": "health"
    },
    {
        "lat": 42.384395,
        "lon": -71.0785978,
        "type": "health"
    },
    {
        "lat": 42.4096205,
        "lon": -71.0295301,
        "type": "health"
    },
    {
        "lat": 42.4074565,
        "lon": -71.0565649,
        "type": "health"
    },
    {
        "lat": 42.3750837,
        "lon": -71.0635142,
        "type": "health"
    },
    {
        "lat": 42.3803692,
        "lon": -71.0256898,
        "type": "health"
    },
    {
        "lat": 42.3944587,
        "lon": -71.0396727,
        "type": "health"
    },
    {
        "lat": 42.393001,
        "lon": -71.04056609999999,
        "type": "health"
    },
    {
        "lat": 42.3920283,
        "lon": -71.0313189,
        "type": "health"
    },
    {
        "lat": 42.3769043,
        "lon": -71.036611,
        "type": "health"
    },
    {
        "lat": 42.3847695,
        "lon": -71.0704834,
        "type": "health"
    },
    {
        "lat": 42.3722919,
        "lon": -71.0884284,
        "type": "health"
    },
    {
        "lat": 42.4208408,
        "lon": -71.0159895,
        "type": "health"
    }
]